odoo/addons/product_category_description/README.rst
odoo/addons/product_category_description/__init__.py
odoo/addons/product_category_description/__manifest__.py
odoo/addons/product_category_description/i18n/it.po
odoo/addons/product_category_description/i18n/product_category_description.pot
odoo/addons/product_category_description/models/__init__.py
odoo/addons/product_category_description/models/product_category.py
odoo/addons/product_category_description/readme/CONTRIBUTORS.rst
odoo/addons/product_category_description/readme/DESCRIPTION.rst
odoo/addons/product_category_description/static/description/icon.png
odoo/addons/product_category_description/static/description/index.html
odoo/addons/product_category_description/views/product_category.xml
odoo13_addon_product_category_description-13.0.1.0.1.dev5.dist-info/METADATA
odoo13_addon_product_category_description-13.0.1.0.1.dev5.dist-info/WHEEL
odoo13_addon_product_category_description-13.0.1.0.1.dev5.dist-info/top_level.txt
odoo13_addon_product_category_description-13.0.1.0.1.dev5.dist-info/RECORD
